pioneergame/Fixedsys.ttf
pioneergame/__init__.py
pioneergame/arrow.py
pioneergame/brick.png
pioneergame/bush.png
pioneergame/button.py
pioneergame/circle.py
pioneergame/explosion.py
pioneergame/green_tank.png
pioneergame/label.py
pioneergame/metal.png
pioneergame/missing_texture.png
pioneergame/presets.py
pioneergame/rect.py
pioneergame/ruler.py
pioneergame/sprite.py
pioneergame/sprites.py
pioneergame/window.py
pioneergame/yellow_tank.png
pioneergame-0.0.33.dist-info/METADATA
pioneergame-0.0.33.dist-info/WHEEL
pioneergame-0.0.33.dist-info/top_level.txt
pioneergame-0.0.33.dist-info/RECORD
