Metadata-Version: 2.4
Name: pioneergame
Version: 0.0.33
Summary: Simple Pygame wrap for small kids
Home-page: https://github.com/chebur5581/pioneergame
Author: chebur5581
Author-email: chebur5581@gmail.com
Project-URL: GitHub, https://github.com/chebur5581/pioneergame
Keywords: Games Pygame kis Learning pioneergame
Classifier: Programming Language :: Python :: 3.11
Classifier: Operating System :: Microsoft :: Windows
Requires-Python: >=3.12
Requires-Dist: pygame-ce>=2.5.0
Requires-Dist: setuptools
Dynamic: author
Dynamic: author-email
Dynamic: classifier
Dynamic: description
Dynamic: description-content-type
Dynamic: home-page
Dynamic: keywords
Dynamic: project-url
Dynamic: requires-dist
Dynamic: requires-python
Dynamic: summary
